counter.sv
module counter(
	input logic 	clk,
	input logic 	rst_n,
	input logic 	en,
	
	output logic [7:0] count
);

	always_ff @(posedge clk or negedge rst_n) begin
		if (!rst_n)
			count <= 8'b0;
		else if (en) 
			count <= count +1;
	end
endmodule

tb_counter.sv
module tb_counter;
	logic 	clk, rst_n, en;
	logic [7:0] count;
	
	counter dut (.*); //auto connect
	
	initial clk = 0;
	always #5 clk = ~clk; // Clock 10ns (100MHz)
	
	initial begin 
		$dumpfile("counter.vcd");
		$dumpvars(0, tb_counter);
		
		rst_n = 0; en =0; // Reset
		#20;
		rst_n = 1; en = 1; // Start counting
		#200;
		en = 0; //Stop counting
		#50;
		en = 1; // Start counting
		#100;
		$display("Final count = %0d", count);
		$finish;
	end
	
endmodule

counter.vcd
$date
	Tue Mar 31 15:47:00 2026
$end
$version
	Icarus Verilog
$end
$timescale
	1s
$end
$scope module tb_counter $end
$var wire 8 ! count [7:0] $end
$var reg 1 " clk $end
$var reg 1 # en $end
$var reg 1 $ rst_n $end
$scope module dut $end
$var wire 1 " clk $end
$var wire 1 # en $end
$var wire 1 $ rst_n $end
$var reg 8 % count [7:0] $end
$upscope $end
$upscope $end
$enddefinitions $end
$comment Show the parameter values. $end
$dumpall
$end
#0
$dumpvars
b0 %
0$
0#
0"
b0 !
$end
#5
1"
#10
0"
#15
1"
#20
0"
1#
1$
#25
b1 !
b1 %
1"
#30
0"
#35
b10 !
b10 %
1"
#40
0"
#45
b11 !
b11 %
1"
#50
0"
#55
b100 !
b100 %
1"
#60
0"
#65
b101 !
b101 %
1"
#70
0"
#75
b110 !
b110 %
1"
#80
0"
#85
b111 !
b111 %
1"
#90
0"
#95
b1000 !
b1000 %
1"
#100
0"
#105
b1001 !
b1001 %
1"
#110
0"
#115
b1010 !
b1010 %
1"
#120
0"
#125
b1011 !
b1011 %
1"
#130
0"
#135
b1100 !
b1100 %
1"
#140
0"
#145
b1101 !
b1101 %
1"
#150
0"
#155
b1110 !
b1110 %
1"
#160
0"
#165
b1111 !
b1111 %
1"
#170
0"
#175
b10000 !
b10000 %
1"
#180
0"
#185
b10001 !
b10001 %
1"
#190
0"
#195
b10010 !
b10010 %
1"
#200
0"
#205
b10011 !
b10011 %
1"
#210
0"
#215
b10100 !
b10100 %
1"
#220
0"
0#
#225
1"
#230
0"
#235
1"
#240
0"
#245
1"
#250
0"
#255
1"
#260
0"
#265
1"
#270
0"
1#
#275
b10101 !
b10101 %
1"
#280
0"
#285
b10110 !
b10110 %
1"
#290
0"
#295
b10111 !
b10111 %
1"
#300
0"
#305
b11000 !
b11000 %
1"
#310
0"
#315
b11001 !
b11001 %
1"
#320
0"
#325
b11010 !
b11010 %
1"
#330
0"
#335
b11011 !
b11011 %
1"
#340
0"
#345
b11100 !
b11100 %
1"
#350
0"
#355
b11101 !
b11101 %
1"
#360
0"
#365
b11110 !
b11110 %
1"
